CHANGES.txt
LICENSE
MANIFEST.in
README.rst
setup.py
mldissect/__init__.py
mldissect/explainer.py
mldissect/explanation.py
mldissect/utils.py
mldissect.egg-info/PKG-INFO
mldissect.egg-info/SOURCES.txt
mldissect.egg-info/dependency_links.txt
mldissect.egg-info/requires.txt
mldissect.egg-info/top_level.txt
mldissect.egg-info/zip-safe