Metadata-Version: 1.1
Name: mldissect
Version: 0.0.1a0
Summary: mldissect - model agnostic explanations
Home-page: https://github.com/ml-libs/mldissect
Author: Nikolay Novik
Author-email: nickolainovik@gmail.com
License: Apache 2
Download-URL: https://pypi.python.org/pypi/mldissect
Keywords: mldissect,model explanation
Platform: POSIX
Classifier: License :: OSI Approved :: Apache Software License
Classifier: Intended Audience :: Developers
Classifier: Programming Language :: Python :: 3
Classifier: Programming Language :: Python :: 3.6
Classifier: Programming Language :: Python :: 3.7
Classifier: Operating System :: POSIX
Classifier: Development Status :: 2 - Pre-Alpha
Classifier: Framework :: AsyncIO
